gui/ui.py
gui/x_epi_app.py
x_epi/XEPI.py
x_epi/__init__.py
x_epi/utils.py
x_epi-0.0.3.dist-info/LICENSE
x_epi-0.0.3.dist-info/METADATA
x_epi-0.0.3.dist-info/WHEEL
x_epi-0.0.3.dist-info/top_level.txt
x_epi-0.0.3.dist-info/RECORD
