Metadata-Version: 2.1
Name: x-epi
Version: 0.0.3
Summary: A package for creating EPI sequences for X-Nuclues imaging
Author-email: Tyler Blazey <blazey@wustl.edu>
Project-URL: Homepage, https://github.com/tblazey/x_epi
Classifier: Programming Language :: Python :: 3
Classifier: License :: OSI Approved :: MIT License
Classifier: Operating System :: OS Independent
Requires-Python: <3.10
License-File: LICENSE
